ikernel_remote
