Metadata-Version: 2.1
Name: ikernel-remote
Version: 1.0.1
Summary: Running IPython kernels remotely and through batch queues
Home-page: https://github.com/macdems/ikernel_remote
Author-email: Tom Daff <tdd20@cam.ac.uk>, Maciej Dems <maciej.dems@p.lodz.pl>
License: BSD
Project-URL: Homepage, https://github.com/macdems/ikernel_remote
Platform: UNKNOWN
Classifier: Programming Language :: Python :: 3
Classifier: Framework :: IPython
Classifier: License :: OSI Approved :: BSD License
Requires-Python: >=3.4
License-File: LICENSE.txt
